README.rst
setup.py
pyffx/__init__.py
pyffx/codecs.py
pyffx/ffx.py
pyffx/tests.py
pyffx.egg-info/PKG-INFO
pyffx.egg-info/SOURCES.txt
pyffx.egg-info/dependency_links.txt
pyffx.egg-info/requires.txt
pyffx.egg-info/top_level.txt