Metadata-Version: 1.1
Name: pyffx
Version: 0.2.0
Summary: pure Python format preserving encryption
Home-page: http://github.com/emulbreh/pyffx/
Author: Johannes Dollinger
Author-email: UNKNOWN
License: BSD License
Platform: UNKNOWN
Classifier: Development Status :: 3 - Alpha
Classifier: Intended Audience :: Developers
Classifier: License :: OSI Approved :: BSD License
Classifier: Operating System :: OS Independent
Classifier: Programming Language :: Python :: 2.7
Classifier: Programming Language :: Python :: 3
